py.typed
speakeasy_client_sdk_python/__init__.py
speakeasy_client_sdk_python/_hooks/__init__.py
speakeasy_client_sdk_python/_hooks/registration.py
speakeasy_client_sdk_python/_hooks/sdkhooks.py
speakeasy_client_sdk_python/_hooks/types.py
speakeasy_client_sdk_python/apiendpoints.py
speakeasy_client_sdk_python/apis.py
speakeasy_client_sdk_python/artifacts.py
speakeasy_client_sdk_python/auth.py
speakeasy_client_sdk_python/basesdk.py
speakeasy_client_sdk_python/embeds.py
speakeasy_client_sdk_python/events.py
speakeasy_client_sdk_python/github.py
speakeasy_client_sdk_python/httpclient.py
speakeasy_client_sdk_python/metadata.py
speakeasy_client_sdk_python/models/errors/__init__.py
speakeasy_client_sdk_python/models/errors/error.py
speakeasy_client_sdk_python/models/errors/sdkerror.py
speakeasy_client_sdk_python/models/internal/__init__.py
speakeasy_client_sdk_python/models/internal/globals.py
speakeasy_client_sdk_python/models/operations/__init__.py
speakeasy_client_sdk_python/models/operations/applyoperationids.py
speakeasy_client_sdk_python/models/operations/checkaccess.py
speakeasy_client_sdk_python/models/operations/configurecodesamples.py
speakeasy_client_sdk_python/models/operations/configuremintlifyrepo.py
speakeasy_client_sdk_python/models/operations/configuretarget.py
speakeasy_client_sdk_python/models/operations/create.py
speakeasy_client_sdk_python/models/operations/createfreetrial.py
speakeasy_client_sdk_python/models/operations/deleteapi.py
speakeasy_client_sdk_python/models/operations/deleteapiendpoint.py
speakeasy_client_sdk_python/models/operations/deleteschema.py
speakeasy_client_sdk_python/models/operations/deleteversionmetadata.py
speakeasy_client_sdk_python/models/operations/downloadschema.py
speakeasy_client_sdk_python/models/operations/downloadschemarevision.py
speakeasy_client_sdk_python/models/operations/fetchpublishingprs.py
speakeasy_client_sdk_python/models/operations/findapiendpoint.py
speakeasy_client_sdk_python-6.3.0.dist-info/METADATA
speakeasy_client_sdk_python-6.3.0.dist-info/WHEEL
speakeasy_client_sdk_python-6.3.0.dist-info/RECORD
